logging3/__init__.py
logging3/handlers.py
logging3-0.0.2.dist-info/LICENSE
logging3-0.0.2.dist-info/METADATA
logging3-0.0.2.dist-info/WHEEL
logging3-0.0.2.dist-info/top_level.txt
logging3-0.0.2.dist-info/RECORD
