Metadata-Version: 2.1
Name: logging3
Version: 0.0.2
Summary: Useful logging enhancement
Home-page: https://github.com/pmayer/logging3
Author: Philipp Mayer
Author-email: dev@paradoxon.at
License: UNKNOWN
Platform: UNKNOWN
Classifier: Programming Language :: Python :: 3
Classifier: License :: OSI Approved :: MIT License
Classifier: Operating System :: OS Independent
